conoha/__init__.py
conoha/conoha.py
conoha-0.1.20.dist-info/LICENSE
conoha-0.1.20.dist-info/METADATA
conoha-0.1.20.dist-info/WHEEL
conoha-0.1.20.dist-info/entry_points.txt
conoha-0.1.20.dist-info/top_level.txt
conoha-0.1.20.dist-info/RECORD
