Metadata-Version: 2.1
Name: conoha
Version: 0.1.20
Summary: A command-line interface to the ConoHa.
Home-page: https://github.com/giginc/conoha
Author: Shogo Ishikura
Author-email: ishikura_shogo@giginc.co.jp
License: MIT
Platform: UNKNOWN
License-File: LICENSE
Requires-Dist: click
Requires-Dist: requests
Requires-Dist: toml
